inter_rao_energosbyt/__init__.py
inter_rao_energosbyt/const.py
inter_rao_energosbyt/converters.py
inter_rao_energosbyt/enums.py
inter_rao_energosbyt/exceptions.py
inter_rao_energosbyt/interfaces.py
inter_rao_energosbyt/util.py
inter_rao_energosbyt/actions/__init__.py
inter_rao_energosbyt/actions/_bases.py
inter_rao_energosbyt/actions/auth.py
inter_rao_energosbyt/actions/invalidate.py
inter_rao_energosbyt/actions/sql/__init__.py
inter_rao_energosbyt/actions/sql/abonent.py
inter_rao_energosbyt/actions/sql/ads.py
inter_rao_energosbyt/actions/sql/attributes.py
inter_rao_energosbyt/actions/sql/auto_payment.py
inter_rao_energosbyt/actions/sql/byt.py
inter_rao_energosbyt/actions/sql/core.py
inter_rao_energosbyt/actions/sql/crm.py
inter_rao_energosbyt/actions/sql/dt_cache.py
inter_rao_energosbyt/actions/sql/elements.py
inter_rao_energosbyt/actions/sql/faq.py
inter_rao_energosbyt/actions/sql/generic.py
inter_rao_energosbyt/actions/sql/ls_generic.py
inter_rao_energosbyt/actions/sql/ls_management.py
inter_rao_energosbyt/actions/sql/ls_privileges.py
inter_rao_energosbyt/actions/sql/metadata.py
inter_rao_energosbyt/actions/sql/multiple_payment.py
inter_rao_energosbyt/actions/sql/other.py
inter_rao_energosbyt/actions/sql/paid_services.py
inter_rao_energosbyt/actions/sql/prepay_params.py
inter_rao_energosbyt/actions/sql/privileges_avail.py
inter_rao_energosbyt/actions/sql/profile.py
inter_rao_energosbyt/actions/sql/subscriber.py
inter_rao_energosbyt/actions/sql/subscription.py
inter_rao_energosbyt/actions/sql/view.py
inter_rao_energosbyt/actions/sql/specific/__init__.py
inter_rao_energosbyt/actions/sql/specific/ksg.py
inter_rao_energosbyt/actions/sql/specific/mes.py
inter_rao_energosbyt/actions/sql/specific/moe.py
inter_rao_energosbyt/actions/sql/specific/sar.py
inter_rao_energosbyt/actions/sql/specific/tmk.py
inter_rao_energosbyt/actions/sql/specific/ufa.py
inter_rao_energosbyt/api/__init__.py
inter_rao_energosbyt/api/altai.py
inter_rao_energosbyt/api/bashkortostan.py
inter_rao_energosbyt_python_raykeen-0.0.26.dist-info/METADATA
inter_rao_energosbyt_python_raykeen-0.0.26.dist-info/WHEEL
inter_rao_energosbyt_python_raykeen-0.0.26.dist-info/top_level.txt
inter_rao_energosbyt_python_raykeen-0.0.26.dist-info/RECORD
